shadowkill_ruh/__init__.py
shadowkill_ruh/core.py
shadowkill_ruh/data/Work_Report_2024.xlsx
shadowkill_ruh-1.0.0.dist-info/licenses/LICENSE
shadowkill_ruh-1.0.0.dist-info/METADATA
shadowkill_ruh-1.0.0.dist-info/WHEEL
shadowkill_ruh-1.0.0.dist-info/entry_points.txt
shadowkill_ruh-1.0.0.dist-info/top_level.txt
shadowkill_ruh-1.0.0.dist-info/RECORD
