Metadata-Version: 2.4
Name: shadowkill_ruh
Version: 1.0.0
Summary: Audio-triggered panic system that instantly closes browsers and opens Excel
Author-email: Rushan Ul Haque <your.email@example.com>
License: MIT
Project-URL: Homepage, https://github.com/rushanhaque/Shadow-chat
Project-URL: Repository, https://github.com/rushanhaque/Shadow-chat
Project-URL: Issues, https://github.com/rushanhaque/Shadow-chat/issues
Keywords: productivity,automation,privacy,panic-button,browser-control
Classifier: Development Status :: 4 - Beta
Classifier: Intended Audience :: End Users/Desktop
Classifier: License :: OSI Approved :: MIT License
Classifier: Operating System :: Microsoft :: Windows
Classifier: Programming Language :: Python :: 3
Classifier: Programming Language :: Python :: 3.8
Classifier: Programming Language :: Python :: 3.9
Classifier: Programming Language :: Python :: 3.10
Classifier: Programming Language :: Python :: 3.11
Classifier: Programming Language :: Python :: 3.12
Classifier: Topic :: Desktop Environment
Classifier: Topic :: System :: Monitoring
Classifier: Topic :: Utilities
Requires-Python: >=3.8
License-File: LICENSE
Requires-Dist: sounddevice>=0.4.6
Requires-Dist: numpy>=1.20.0
Requires-Dist: psutil>=5.9.0
Dynamic: license-file
